ffsm/__init__.py
ffsm/mover.py
ffsm-1.0.dist-info/METADATA
ffsm-1.0.dist-info/WHEEL
ffsm-1.0.dist-info/entry_points.txt
ffsm-1.0.dist-info/top_level.txt
ffsm-1.0.dist-info/RECORD
