Metadata-Version: 2.1
Name: ffsm
Version: 1.0
Summary: A utility to rename files with wildcard support
Home-page: UNKNOWN
Author: Chowdhury Faizal Ahammed
License: UNKNOWN
Keywords: ffsm
Platform: UNKNOWN
